rerouter/__init__.py
rerouter/router.py
rerouter-0.0.2.dist-info/LICENSE.txt
rerouter-0.0.2.dist-info/METADATA
rerouter-0.0.2.dist-info/WHEEL
rerouter-0.0.2.dist-info/top_level.txt
rerouter-0.0.2.dist-info/RECORD
