Metadata-Version: 2.1
Name: rerouter
Version: 0.0.2
Summary: RegEx based router
Home-page: https://github.com/shijinglu/rerouter
Author: Shijing Lu
Author-email: shijing.lv@gmail.com
Project-URL: Bug Reports, https://github.com/shijinglu/rerouter/issues
Project-URL: Say Thanks!, https://saythanks.io/to/shijinglu
Project-URL: Source, https://github.com/shijinglu/rerouter/
Keywords: router,setuptools,development
Classifier: Development Status :: 3 - Alpha
Classifier: Intended Audience :: Developers
Classifier: Topic :: Software Development :: Build Tools
Classifier: License :: OSI Approved :: MIT License
Classifier: Programming Language :: Python :: 3
Classifier: Programming Language :: Python :: 3.7
Classifier: Programming Language :: Python :: 3.8
Classifier: Programming Language :: Python :: 3.9
Classifier: Programming Language :: Python :: 3.10
Classifier: Programming Language :: Python :: 3 :: Only
Requires-Python: >=3.7, <4
License-File: LICENSE.txt
Requires-Dist: peppercorn
Provides-Extra: dev
Requires-Dist: check-manifest ; extra == 'dev'
Provides-Extra: test
Requires-Dist: coverage ; extra == 'test'
